README.md
setup.py
bin/shmr
shmr/__init__.py
shmr/__main__.py
shmr/funcs.py
shmr/main.py
shmr/misc.py
shmr/partition.py
shmr/partition_writer.py
shmr/partitions.py
shmr/version.py
shmr.egg-info/PKG-INFO
shmr.egg-info/SOURCES.txt
shmr.egg-info/dependency_links.txt
shmr.egg-info/requires.txt
shmr.egg-info/top_level.txt
tests/__init__.py
tests/conftest.py
tests/test_partition.py
tests/test_partitions.py