Metadata-Version: 2.1
Name: shmr
Version: 1.4.5
Summary: A set of map-reduce high-order functions to use with parallel or xargs
Home-page: https://github.com/binh-vu/shmr
Author: Binh Vu
Author-email: binh@toan2.com
License: MIT
Platform: UNKNOWN
Requires-Python: >3.6
